vmxai_extraction/__init__.py
vmxai_extraction/sfn/__init__.py
vmxai_extraction/sfn/local_similarity_search/__init__.py
vmxai_extraction/sfn/local_similarity_search/decorator.py
vmxai_extraction/sfn/local_similarity_search/types.py
vmxai_extraction/sfn/split/__init__.py
vmxai_extraction/sfn/split/decorator.py
vmxai_extraction/sfn/split/types.py
vmxai_extraction/sfn/store_embedding/__init__.py
vmxai_extraction/sfn/store_embedding/decorator.py
vmxai_extraction/sfn/store_embedding/types.py
vmxai_extraction/sfn/types.py
vmxai_extraction/utils.py
vm_x_ai_extraction-0.1.1.dist-info/METADATA
vm_x_ai_extraction-0.1.1.dist-info/WHEEL
vm_x_ai_extraction-0.1.1.dist-info/RECORD
